LICENSE.txt
MANIFEST.in
README.rst
setup.cfg
setup.py
yosstocks/TickersData.py
yosstocks/__init__.py
yosstocks.egg-info/PKG-INFO
yosstocks.egg-info/SOURCES.txt
yosstocks.egg-info/dependency_links.txt
yosstocks.egg-info/top_level.txt