Metadata-Version: 1.0
Name: yosstocks
Version: 0.5
Summary: this is an api for stocks analysis
Home-page: https://github.com/houhashv
Author: houhashv
Author-email: yossihohashvili1@gmail.com
License: UNKNOWN
Platform: UNKNOWN
